{
  "product": {
    "productSlug": "wave2-ambu-neuroline-cup",
    "manufacturer": "Ambu",
    "productName": "Ambu Neuroline Cup",
    "model": "Neuroline Cup",
    "category": "Неврологические расходные материалы"
  },
  "reviewItems": [
    {
      "reviewItemId": "review_item_5ad05ec5056ed927cdb2058e",
      "productSlug": "wave2-ambu-neuroline-cup",
      "productTitle": "Ambu Neuroline Cup",
      "claimCandidateId": "claim_70040c63c6fcc9fe6d017e8a",
      "suggestedClaimType": "document.title",
      "valuePayload": {
        "value": "IFU Ambu® Neuroline Cup V02 2023/11",
        "unit": null
      },
      "evidenceCandidateIds": [
        "evidence_acd014de6d29a56243cc7256"
      ],
      "documentVersionIds": [
        "document_version_387da1aa8f7f35ec7914f098"
      ],
      "sourceUrls": [
        "https://www.ambu.com/Admin/Public/DWSDownload.aspx?File=%2fFiles%2fFiles%2fDownloads%2fAmbu+com%2fNeurology%2fEEG_electrodes%2fNeuroline+Cup%2fInstructions+for+use%2f492726000-IFU-Neuroline-Cup-726-surface-electrodes_Multi_V02_202311_TCC-11245_Online.pdf"
      ],
      "status": "pending_review",
      "priority": "medium",
      "riskLevel": "low",
      "reasons": [
        "Document metadata or low-level extracted term requires review.",
        "Review Queue item is not a Verified Claim.",
        "Reviewer decision does not publish data."
      ],
      "reviewerNotes": null,
      "createdAt": "candidate-review-queue",
      "updatedAt": "candidate-review-queue"
    },
    {
      "reviewItemId": "review_item_b1a6ffe88e3a913a8e1cc031",
      "productSlug": "wave2-ambu-neuroline-cup",
      "productTitle": "Ambu Neuroline Cup",
      "claimCandidateId": "claim_75a1b9b5111ff3f52e05161f",
      "suggestedClaimType": "document.type",
      "valuePayload": {
        "value": "ifu",
        "unit": null
      },
      "evidenceCandidateIds": [
        "evidence_1c9cad2be1a0274db5f9ea8b"
      ],
      "documentVersionIds": [
        "document_version_387da1aa8f7f35ec7914f098"
      ],
      "sourceUrls": [
        "https://www.ambu.com/Admin/Public/DWSDownload.aspx?File=%2fFiles%2fFiles%2fDownloads%2fAmbu+com%2fNeurology%2fEEG_electrodes%2fNeuroline+Cup%2fInstructions+for+use%2f492726000-IFU-Neuroline-Cup-726-surface-electrodes_Multi_V02_202311_TCC-11245_Online.pdf"
      ],
      "status": "pending_review",
      "priority": "medium",
      "riskLevel": "low",
      "reasons": [
        "Document metadata or low-level extracted term requires review.",
        "Review Queue item is not a Verified Claim.",
        "Reviewer decision does not publish data."
      ],
      "reviewerNotes": null,
      "createdAt": "candidate-review-queue",
      "updatedAt": "candidate-review-queue"
    },
    {
      "reviewItemId": "review_item_530c1d05f65e941c5ea29380",
      "productSlug": "wave2-ambu-neuroline-cup",
      "productTitle": "Ambu Neuroline Cup",
      "claimCandidateId": "claim_297cc3d44d51844f829f7a05",
      "suggestedClaimType": "technical.term",
      "valuePayload": {
        "value": "weight",
        "unit": null
      },
      "evidenceCandidateIds": [
        "evidence_1c669a36140505486870c6fd"
      ],
      "documentVersionIds": [
        "document_version_387da1aa8f7f35ec7914f098"
      ],
      "sourceUrls": [
        "https://www.ambu.com/Admin/Public/DWSDownload.aspx?File=%2fFiles%2fFiles%2fDownloads%2fAmbu+com%2fNeurology%2fEEG_electrodes%2fNeuroline+Cup%2fInstructions+for+use%2f492726000-IFU-Neuroline-Cup-726-surface-electrodes_Multi_V02_202311_TCC-11245_Online.pdf"
      ],
      "status": "pending_review",
      "priority": "medium",
      "riskLevel": "low",
      "reasons": [
        "Document metadata or low-level extracted term requires review.",
        "Review Queue item is not a Verified Claim.",
        "Reviewer decision does not publish data."
      ],
      "reviewerNotes": null,
      "createdAt": "candidate-review-queue",
      "updatedAt": "candidate-review-queue"
    },
    {
      "reviewItemId": "review_item_b8baaa2b1d6e633ecbc0e4b4",
      "productSlug": "wave2-ambu-neuroline-cup",
      "productTitle": "Ambu Neuroline Cup",
      "claimCandidateId": "claim_709347dff9aa04d8b7f42138",
      "suggestedClaimType": "document.title",
      "valuePayload": {
        "value": "Ambu Neuroline Cup datasheet V02 2022/07",
        "unit": null
      },
      "evidenceCandidateIds": [
        "evidence_51c3c2c5082507c37437f786"
      ],
      "documentVersionIds": [
        "document_version_d07f3f65a3611f3d46fe3be6"
      ],
      "sourceUrls": [
        "https://www.ambu.com/Admin/Public/Download.aspx?file=Files%2FFiles%2FDownloads%2FAmbu+com%2FNeurology%2FEEG_electrodes%2FNeuroline+Cup%2FDatasheets%2FLBL-006791-Datasheet-Ambu-Neuroline-Cup-726_IE_V2_202207_TCC-11330.pdf"
      ],
      "status": "pending_review",
      "priority": "medium",
      "riskLevel": "low",
      "reasons": [
        "Document metadata or low-level extracted term requires review.",
        "Review Queue item is not a Verified Claim.",
        "Reviewer decision does not publish data."
      ],
      "reviewerNotes": null,
      "createdAt": "candidate-review-queue",
      "updatedAt": "candidate-review-queue"
    },
    {
      "reviewItemId": "review_item_81e94c8fc93b6c8470a1f686",
      "productSlug": "wave2-ambu-neuroline-cup",
      "productTitle": "Ambu Neuroline Cup",
      "claimCandidateId": "claim_b631dc9a18ee8c4f007c28d8",
      "suggestedClaimType": "document.language",
      "valuePayload": {
        "value": "en",
        "unit": null
      },
      "evidenceCandidateIds": [
        "evidence_4e202406f61c9aaee1dd50df"
      ],
      "documentVersionIds": [
        "document_version_d07f3f65a3611f3d46fe3be6"
      ],
      "sourceUrls": [
        "https://www.ambu.com/Admin/Public/Download.aspx?file=Files%2FFiles%2FDownloads%2FAmbu+com%2FNeurology%2FEEG_electrodes%2FNeuroline+Cup%2FDatasheets%2FLBL-006791-Datasheet-Ambu-Neuroline-Cup-726_IE_V2_202207_TCC-11330.pdf"
      ],
      "status": "pending_review",
      "priority": "medium",
      "riskLevel": "medium",
      "reasons": [
        "Candidate claim requires human review before verification.",
        "Review Queue item is not a Verified Claim.",
        "Reviewer decision does not publish data."
      ],
      "reviewerNotes": null,
      "createdAt": "candidate-review-queue",
      "updatedAt": "candidate-review-queue"
    },
    {
      "reviewItemId": "review_item_25084399034c55d55f9f6cf1",
      "productSlug": "wave2-ambu-neuroline-cup",
      "productTitle": "Ambu Neuroline Cup",
      "claimCandidateId": "claim_ee253268901f6eca904e4044",
      "suggestedClaimType": "document.type",
      "valuePayload": {
        "value": "datasheet",
        "unit": null
      },
      "evidenceCandidateIds": [
        "evidence_94d1bd38384a0642a8f8afd2"
      ],
      "documentVersionIds": [
        "document_version_d07f3f65a3611f3d46fe3be6"
      ],
      "sourceUrls": [
        "https://www.ambu.com/Admin/Public/Download.aspx?file=Files%2FFiles%2FDownloads%2FAmbu+com%2FNeurology%2FEEG_electrodes%2FNeuroline+Cup%2FDatasheets%2FLBL-006791-Datasheet-Ambu-Neuroline-Cup-726_IE_V2_202207_TCC-11330.pdf"
      ],
      "status": "pending_review",
      "priority": "medium",
      "riskLevel": "low",
      "reasons": [
        "Document metadata or low-level extracted term requires review.",
        "Review Queue item is not a Verified Claim.",
        "Reviewer decision does not publish data."
      ],
      "reviewerNotes": null,
      "createdAt": "candidate-review-queue",
      "updatedAt": "candidate-review-queue"
    }
  ],
  "groupedByClaimType": {
    "document.title": [
      {
        "reviewItemId": "review_item_5ad05ec5056ed927cdb2058e",
        "productSlug": "wave2-ambu-neuroline-cup",
        "productTitle": "Ambu Neuroline Cup",
        "claimCandidateId": "claim_70040c63c6fcc9fe6d017e8a",
        "suggestedClaimType": "document.title",
        "valuePayload": {
          "value": "IFU Ambu® Neuroline Cup V02 2023/11",
          "unit": null
        },
        "evidenceCandidateIds": [
          "evidence_acd014de6d29a56243cc7256"
        ],
        "documentVersionIds": [
          "document_version_387da1aa8f7f35ec7914f098"
        ],
        "sourceUrls": [
          "https://www.ambu.com/Admin/Public/DWSDownload.aspx?File=%2fFiles%2fFiles%2fDownloads%2fAmbu+com%2fNeurology%2fEEG_electrodes%2fNeuroline+Cup%2fInstructions+for+use%2f492726000-IFU-Neuroline-Cup-726-surface-electrodes_Multi_V02_202311_TCC-11245_Online.pdf"
        ],
        "status": "pending_review",
        "priority": "medium",
        "riskLevel": "low",
        "reasons": [
          "Document metadata or low-level extracted term requires review.",
          "Review Queue item is not a Verified Claim.",
          "Reviewer decision does not publish data."
        ],
        "reviewerNotes": null,
        "createdAt": "candidate-review-queue",
        "updatedAt": "candidate-review-queue"
      },
      {
        "reviewItemId": "review_item_b8baaa2b1d6e633ecbc0e4b4",
        "productSlug": "wave2-ambu-neuroline-cup",
        "productTitle": "Ambu Neuroline Cup",
        "claimCandidateId": "claim_709347dff9aa04d8b7f42138",
        "suggestedClaimType": "document.title",
        "valuePayload": {
          "value": "Ambu Neuroline Cup datasheet V02 2022/07",
          "unit": null
        },
        "evidenceCandidateIds": [
          "evidence_51c3c2c5082507c37437f786"
        ],
        "documentVersionIds": [
          "document_version_d07f3f65a3611f3d46fe3be6"
        ],
        "sourceUrls": [
          "https://www.ambu.com/Admin/Public/Download.aspx?file=Files%2FFiles%2FDownloads%2FAmbu+com%2FNeurology%2FEEG_electrodes%2FNeuroline+Cup%2FDatasheets%2FLBL-006791-Datasheet-Ambu-Neuroline-Cup-726_IE_V2_202207_TCC-11330.pdf"
        ],
        "status": "pending_review",
        "priority": "medium",
        "riskLevel": "low",
        "reasons": [
          "Document metadata or low-level extracted term requires review.",
          "Review Queue item is not a Verified Claim.",
          "Reviewer decision does not publish data."
        ],
        "reviewerNotes": null,
        "createdAt": "candidate-review-queue",
        "updatedAt": "candidate-review-queue"
      }
    ],
    "document.type": [
      {
        "reviewItemId": "review_item_b1a6ffe88e3a913a8e1cc031",
        "productSlug": "wave2-ambu-neuroline-cup",
        "productTitle": "Ambu Neuroline Cup",
        "claimCandidateId": "claim_75a1b9b5111ff3f52e05161f",
        "suggestedClaimType": "document.type",
        "valuePayload": {
          "value": "ifu",
          "unit": null
        },
        "evidenceCandidateIds": [
          "evidence_1c9cad2be1a0274db5f9ea8b"
        ],
        "documentVersionIds": [
          "document_version_387da1aa8f7f35ec7914f098"
        ],
        "sourceUrls": [
          "https://www.ambu.com/Admin/Public/DWSDownload.aspx?File=%2fFiles%2fFiles%2fDownloads%2fAmbu+com%2fNeurology%2fEEG_electrodes%2fNeuroline+Cup%2fInstructions+for+use%2f492726000-IFU-Neuroline-Cup-726-surface-electrodes_Multi_V02_202311_TCC-11245_Online.pdf"
        ],
        "status": "pending_review",
        "priority": "medium",
        "riskLevel": "low",
        "reasons": [
          "Document metadata or low-level extracted term requires review.",
          "Review Queue item is not a Verified Claim.",
          "Reviewer decision does not publish data."
        ],
        "reviewerNotes": null,
        "createdAt": "candidate-review-queue",
        "updatedAt": "candidate-review-queue"
      },
      {
        "reviewItemId": "review_item_25084399034c55d55f9f6cf1",
        "productSlug": "wave2-ambu-neuroline-cup",
        "productTitle": "Ambu Neuroline Cup",
        "claimCandidateId": "claim_ee253268901f6eca904e4044",
        "suggestedClaimType": "document.type",
        "valuePayload": {
          "value": "datasheet",
          "unit": null
        },
        "evidenceCandidateIds": [
          "evidence_94d1bd38384a0642a8f8afd2"
        ],
        "documentVersionIds": [
          "document_version_d07f3f65a3611f3d46fe3be6"
        ],
        "sourceUrls": [
          "https://www.ambu.com/Admin/Public/Download.aspx?file=Files%2FFiles%2FDownloads%2FAmbu+com%2FNeurology%2FEEG_electrodes%2FNeuroline+Cup%2FDatasheets%2FLBL-006791-Datasheet-Ambu-Neuroline-Cup-726_IE_V2_202207_TCC-11330.pdf"
        ],
        "status": "pending_review",
        "priority": "medium",
        "riskLevel": "low",
        "reasons": [
          "Document metadata or low-level extracted term requires review.",
          "Review Queue item is not a Verified Claim.",
          "Reviewer decision does not publish data."
        ],
        "reviewerNotes": null,
        "createdAt": "candidate-review-queue",
        "updatedAt": "candidate-review-queue"
      }
    ],
    "technical.term": [
      {
        "reviewItemId": "review_item_530c1d05f65e941c5ea29380",
        "productSlug": "wave2-ambu-neuroline-cup",
        "productTitle": "Ambu Neuroline Cup",
        "claimCandidateId": "claim_297cc3d44d51844f829f7a05",
        "suggestedClaimType": "technical.term",
        "valuePayload": {
          "value": "weight",
          "unit": null
        },
        "evidenceCandidateIds": [
          "evidence_1c669a36140505486870c6fd"
        ],
        "documentVersionIds": [
          "document_version_387da1aa8f7f35ec7914f098"
        ],
        "sourceUrls": [
          "https://www.ambu.com/Admin/Public/DWSDownload.aspx?File=%2fFiles%2fFiles%2fDownloads%2fAmbu+com%2fNeurology%2fEEG_electrodes%2fNeuroline+Cup%2fInstructions+for+use%2f492726000-IFU-Neuroline-Cup-726-surface-electrodes_Multi_V02_202311_TCC-11245_Online.pdf"
        ],
        "status": "pending_review",
        "priority": "medium",
        "riskLevel": "low",
        "reasons": [
          "Document metadata or low-level extracted term requires review.",
          "Review Queue item is not a Verified Claim.",
          "Reviewer decision does not publish data."
        ],
        "reviewerNotes": null,
        "createdAt": "candidate-review-queue",
        "updatedAt": "candidate-review-queue"
      }
    ],
    "document.language": [
      {
        "reviewItemId": "review_item_81e94c8fc93b6c8470a1f686",
        "productSlug": "wave2-ambu-neuroline-cup",
        "productTitle": "Ambu Neuroline Cup",
        "claimCandidateId": "claim_b631dc9a18ee8c4f007c28d8",
        "suggestedClaimType": "document.language",
        "valuePayload": {
          "value": "en",
          "unit": null
        },
        "evidenceCandidateIds": [
          "evidence_4e202406f61c9aaee1dd50df"
        ],
        "documentVersionIds": [
          "document_version_d07f3f65a3611f3d46fe3be6"
        ],
        "sourceUrls": [
          "https://www.ambu.com/Admin/Public/Download.aspx?file=Files%2FFiles%2FDownloads%2FAmbu+com%2FNeurology%2FEEG_electrodes%2FNeuroline+Cup%2FDatasheets%2FLBL-006791-Datasheet-Ambu-Neuroline-Cup-726_IE_V2_202207_TCC-11330.pdf"
        ],
        "status": "pending_review",
        "priority": "medium",
        "riskLevel": "medium",
        "reasons": [
          "Candidate claim requires human review before verification.",
          "Review Queue item is not a Verified Claim.",
          "Reviewer decision does not publish data."
        ],
        "reviewerNotes": null,
        "createdAt": "candidate-review-queue",
        "updatedAt": "candidate-review-queue"
      }
    ]
  },
  "sourceDocumentSummary": [
    {
      "documentVersionId": "document_version_387da1aa8f7f35ec7914f098",
      "documentType": "ifu",
      "title": "IFU Ambu® Neuroline Cup V02 2023/11",
      "sourceUrl": "https://www.ambu.com/Admin/Public/DWSDownload.aspx?File=%2fFiles%2fFiles%2fDownloads%2fAmbu+com%2fNeurology%2fEEG_electrodes%2fNeuroline+Cup%2fInstructions+for+use%2f492726000-IFU-Neuroline-Cup-726-surface-electrodes_Multi_V02_202311_TCC-11245_Online.pdf",
      "sha256": "dbd840027206445a8eb99358753908069ca609369ff918421792bab6c5819152"
    },
    {
      "documentVersionId": "document_version_d07f3f65a3611f3d46fe3be6",
      "documentType": "datasheet",
      "title": "Ambu Neuroline Cup datasheet V02 2022/07",
      "sourceUrl": "https://www.ambu.com/Admin/Public/Download.aspx?file=Files%2FFiles%2FDownloads%2FAmbu+com%2FNeurology%2FEEG_electrodes%2FNeuroline+Cup%2FDatasheets%2FLBL-006791-Datasheet-Ambu-Neuroline-Cup-726_IE_V2_202207_TCC-11330.pdf",
      "sha256": "554340becb6c385032926d052a2b009aa1fe7f634c4945362bb8e474e95f4861"
    }
  ],
  "missingEvidence": [],
  "recommendedReviewerAction": "Review extracted candidate claims against linked document versions. Do not publish from this queue.",
  "warnings": [
    "Resolver adapter used: ambu",
    "Resolver rejected offsite document URL: https://twitter.com/Ambueurope",
    "Resolver rejected offsite document URL: https://dk.linkedin.com/company/ambu-as",
    "Resolver rejected offsite document URL: https://www.youtube.com/channel/UCdFCtJCfbWVU6bKUjrmsIQg",
    "Resolver rejected unsafe document URL: javascript:history.back();",
    "Resolver rejected offsite document URL: https://d1jhm577bx9zey.cloudfront.net/Files/%7B%7B%7Bfilepath%7D%7D%7D/%7B%7B%7Bfilename%7D%7D%7D",
    "Resolver rejected offsite document URL: https://www.ambu.co.uk/",
    "Resolver rejected offsite document URL: https://www.ambu.de/",
    "Resolver rejected offsite document URL: https://www.ambu.fr/",
    "Resolver rejected offsite document URL: https://www.ambu.es/",
    "Resolver rejected offsite document URL: https://www.ambu.pt/",
    "Resolver rejected offsite document URL: https://www.ambu.it/",
    "Resolver rejected offsite document URL: https://www.ambu.dk/",
    "Resolver rejected offsite document URL: https://www.ambu.no/",
    "Resolver rejected offsite document URL: https://www.ambu.se/",
    "Resolver rejected offsite document URL: https://www.ambu.fi/",
    "Resolver rejected offsite document URL: https://www.ambuusa.com/",
    "Resolver rejected offsite document URL: https://www.ambuusa.com/",
    "Resolver rejected offsite document URL: https://www.ambu.pt/",
    "Resolver rejected offsite document URL: https://www.ambuaustralia.com.au/",
    "Resolver rejected offsite document URL: https://www.ambu.co.jp/",
    "Resolver rejected unsafe document URL: http://ambuchina.com/",
    "Resolver rejected offsite document URL: https://www.ambuasia.com/",
    "Resolver rejected unsafe document URL: javascript:history.back();",
    "Resolver rejected offsite document URL: https://d1jhm577bx9zey.cloudfront.net/Files/%7B%7B%7Bfilepath%7D%7D%7D/%7B%7B%7Bfilename%7D%7D%7D",
    "Resolver rejected offsite document URL: https://www.ambu.co.uk/",
    "Resolver rejected offsite document URL: https://www.ambu.de/",
    "Resolver rejected offsite document URL: https://www.ambu.fr/",
    "Resolver rejected offsite document URL: https://www.ambu.es/",
    "Resolver rejected offsite document URL: https://www.ambu.pt/",
    "Resolver rejected offsite document URL: https://www.ambu.it/",
    "Resolver rejected offsite document URL: https://www.ambu.dk/",
    "Resolver rejected offsite document URL: https://www.ambu.no/",
    "Resolver rejected offsite document URL: https://www.ambu.se/",
    "Resolver rejected offsite document URL: https://www.ambu.fi/",
    "Resolver rejected offsite document URL: https://www.ambuusa.com/",
    "Resolver rejected offsite document URL: https://www.ambuusa.com/",
    "Resolver rejected offsite document URL: https://www.ambu.pt/",
    "Resolver rejected offsite document URL: https://www.ambuaustralia.com.au/",
    "Resolver rejected offsite document URL: https://www.ambu.co.jp/",
    "Resolver rejected unsafe document URL: http://ambuchina.com/",
    "Resolver rejected offsite document URL: https://www.ambuasia.com/",
    "Resolver rejected unsafe document URL: mailto:tisc@ambu.com",
    "Resolver rejected offsite document URL: https://twitter.com/Ambueurope",
    "Resolver rejected offsite document URL: https://dk.linkedin.com/company/ambu-as",
    "Resolver rejected offsite document URL: https://www.youtube.com/channel/UCdFCtJCfbWVU6bKUjrmsIQg",
    "Resolver rejected unsafe document URL: javascript:history.back();",
    "Resolver rejected offsite document URL: https://d1jhm577bx9zey.cloudfront.net/Files/%7B%7B%7Bfilepath%7D%7D%7D/%7B%7B%7Bfilename%7D%7D%7D",
    "Resolver rejected offsite document URL: https://www.ambu.co.uk/",
    "Resolver rejected offsite document URL: https://www.ambu.de/",
    "Resolver rejected offsite document URL: https://www.ambu.fr/",
    "Resolver rejected offsite document URL: https://www.ambu.es/",
    "Resolver rejected offsite document URL: https://www.ambu.pt/",
    "Resolver rejected offsite document URL: https://www.ambu.it/",
    "Resolver rejected offsite document URL: https://www.ambu.dk/",
    "Resolver rejected offsite document URL: https://www.ambu.no/",
    "Resolver rejected offsite document URL: https://www.ambu.se/",
    "Resolver rejected offsite document URL: https://www.ambu.fi/",
    "Resolver rejected offsite document URL: https://www.ambuusa.com/",
    "Resolver rejected offsite document URL: https://www.ambuusa.com/",
    "Resolver rejected offsite document URL: https://www.ambu.pt/",
    "Resolver rejected offsite document URL: https://www.ambuaustralia.com.au/",
    "Resolver rejected offsite document URL: https://www.ambu.co.jp/",
    "Resolver rejected unsafe document URL: http://ambuchina.com/",
    "Resolver rejected offsite document URL: https://www.ambuasia.com/",
    "Resolver rejected unsafe document URL: http://www.ambuusa.com/corporate-giving",
    "Resolver rejected unsafe document URL: http://www.ambu.com/contact-us",
    "Resolver rejected unsafe document URL: http://www.ambu.com/contact-us",
    "Resolver rejected offsite document URL: https://twitter.com/Ambueurope",
    "Resolver rejected offsite document URL: https://dk.linkedin.com/company/ambu-as",
    "Resolver rejected offsite document URL: https://www.youtube.com/channel/UCdFCtJCfbWVU6bKUjrmsIQg",
    "Resolver rejected unsafe document URL: javascript:history.back();",
    "Resolver rejected offsite document URL: https://d1jhm577bx9zey.cloudfront.net/Files/%7B%7B%7Bfilepath%7D%7D%7D/%7B%7B%7Bfilename%7D%7D%7D",
    "Resolver rejected offsite document URL: https://www.ambu.co.uk/",
    "Resolver rejected offsite document URL: https://www.ambu.de/",
    "Resolver rejected offsite document URL: https://www.ambu.fr/",
    "Resolver rejected offsite document URL: https://www.ambu.es/",
    "Resolver rejected offsite document URL: https://www.ambu.pt/",
    "Resolver rejected offsite document URL: https://www.ambu.it/",
    "Resolver rejected offsite document URL: https://www.ambu.dk/",
    "Resolver rejected offsite document URL: https://www.ambu.no/",
    "Resolver rejected offsite document URL: https://www.ambu.se/",
    "Resolver rejected offsite document URL: https://www.ambu.fi/",
    "Resolver rejected offsite document URL: https://www.ambuusa.com/",
    "Resolver rejected offsite document URL: https://www.ambuusa.com/",
    "Resolver rejected offsite document URL: https://www.ambu.pt/",
    "Resolver rejected offsite document URL: https://www.ambuaustralia.com.au/",
    "Resolver rejected offsite document URL: https://www.ambu.co.jp/",
    "Resolver rejected unsafe document URL: http://ambuchina.com/",
    "Resolver rejected offsite document URL: https://www.ambuasia.com/",
    "resolver=ambu; attempts=4; matchedLinks=18; classifiedDocuments={\"Unknown\":23,\"Brochure\":1,\"Datasheet\":1,\"IFU\":2}; confidenceDistribution={\"80\":13,\"95\":4,\"100\":10}; duplicatesRemoved=9",
    "Discovery creates candidates only; no verified claims or publication."
  ]
}
